{
  "updated_at": "2026/06/16 22:16 JST",
  "market": [
    {
      "name": "TOPIX",
      "value": 3999.6,
      "d1": 3.03,
      "w1": 3.82,
      "m1": 1.07
    },
    {
      "name": "Nikkei225",
      "value": 69317.5,
      "d1": 4.99,
      "w1": 8.27,
      "m1": 4.5
    },
    {
      "name": "S&P500",
      "value": 7511.35,
      "d1": -0.57,
      "w1": 1.69,
      "m1": -0.91
    },
    {
      "name": "TOPIX Banks ETF",
      "value": 706.8,
      "d1": -0.94,
      "w1": 1.54,
      "m1": 7.73
    },
    {
      "name": "Japan Post",
      "value": 2264.5,
      "d1": -0.92,
      "w1": 3.83,
      "m1": 9.5
    },
    {
      "name": "JP Bank",
      "value": 3170.0,
      "d1": -0.88,
      "w1": 0.51,
      "m1": 3.29
    },
    {
      "name": "JGB2Y",
      "value": 1.409,
      "d1": 0.0,
      "w1": null,
      "m1": null
    },
    {
      "name": "JGB5Y",
      "value": 1.901,
      "d1": 0.0,
      "w1": null,
      "m1": null
    },
    {
      "name": "JGB10Y",
      "value": 2.589,
      "d1": 0.0,
      "w1": null,
      "m1": null
    },
    {
      "name": "JGB20Y",
      "value": 3.461,
      "d1": 0.0,
      "w1": null,
      "m1": null
    }
  ]
}